[
	{
		"title": null,
		"caption": "Petit rayon de soleil printanier",
		"subtitle": null,
		"copyright": null,
		"description": null,
		"date": "2024-04-02",
		"bing_url": "https://bing.com/th?id=OHR.JutlandSpring_FR-FR9511410007_UHD.jpg",
		"url": "https://bing.npanuhin.me/FR/fr/2024-04-02.jpg"
	},
	{
		"title": null,
		"caption": "Entre Renaissance et ingéniosité",
		"subtitle": null,
		"copyright": null,
		"description": null,
		"date": "2024-04-03",
		"bing_url": "https://bing.com/th?id=OHR.ChambordCastle_FR-FR1183220484_UHD.jpg",
		"url": "https://bing.npanuhin.me/FR/fr/2024-04-03.jpg"
	},
	{
		"title": null,
		"caption": "Les vagabonds des marais",
		"subtitle": null,
		"copyright": null,
		"description": null,
		"date": "2024-04-04",
		"bing_url": "https://bing.com/th?id=OHR.AntelopeBotswana_FR-FR1380338577_UHD.jpg",
		"url": "https://bing.npanuhin.me/FR/fr/2024-04-04.jpg"
	},
	{
		"title": null,
		"caption": "Le Grand Bleu",
		"subtitle": null,
		"copyright": null,
		"description": null,
		"date": "2024-04-05",
		"bing_url": "https://bing.com/th?id=OHR.BahamasSpace_FR-FR2737935866_UHD.jpg",
		"url": "https://bing.npanuhin.me/FR/fr/2024-04-05.jpg"
	},
	{
		"title": null,
		"caption": "Une vue royale",
		"subtitle": null,
		"copyright": null,
		"description": null,
		"date": "2024-04-06",
		"bing_url": "https://bing.com/th?id=OHR.JapanHimeji_FR-FR4643255326_UHD.jpg",
		"url": "https://bing.npanuhin.me/FR/fr/2024-04-06.jpg"
	},
	{
		"title": null,
		"caption": "Un castor branché !",
		"subtitle": null,
		"copyright": null,
		"description": null,
		"date": "2024-04-07",
		"bing_url": "https://bing.com/th?id=OHR.BeaverDenali_FR-FR4899490419_UHD.jpg",
		"url": "https://bing.npanuhin.me/FR/fr/2024-04-07.jpg"
	},
	{
		"title": null,
		"caption": "Qui s'y frotte, s'y pique !",
		"subtitle": null,
		"copyright": null,
		"description": null,
		"date": "2024-04-08",
		"bing_url": "https://bing.com/th?id=OHR.HedgehogMeadow_FR-FR5225927490_UHD.jpg",
		"url": "https://bing.npanuhin.me/FR/fr/2024-04-08.jpg"
	},
	{
		"title": null,
		"caption": "Tulipe ou pas tulipe ?",
		"subtitle": null,
		"copyright": null,
		"description": null,
		"date": "2024-04-09",
		"bing_url": "https://bing.com/th?id=OHR.SkagitValleyTulips_FR-FR5605427883_UHD.jpg",
		"url": "https://bing.npanuhin.me/FR/fr/2024-04-09.jpg"
	}
]